torchcurves/__init__.py
torchcurves/types.py
torchcurves/functional/__init__.py
torchcurves/functional/_bspline.py
torchcurves/functional/_legendre.py
torchcurves/functional/_normalization.py
torchcurves/modules/__init__.py
torchcurves/modules/_bspline.py
torchcurves/modules/_kan_tools.py
torchcurves/modules/_legendre.py
torchcurves/modules/_normalization.py
torchcurves-0.2.0.dist-info/METADATA
torchcurves-0.2.0.dist-info/WHEEL
torchcurves-0.2.0.dist-info/licenses/LICENSE
torchcurves-0.2.0.dist-info/RECORD
