Metadata-Version: 2.4
Name: torchcurves
Version: 0.2.0
Summary: PyTorch module for differentiable parametric curves with learnable coefficients
Project-URL: Homepage, https://github.com/alexshtf/torchcurves
Project-URL: Repository, https://github.com/alexshtf/torchcurves
Project-URL: Issues, https://github.com/alexshtf/torchcurves/issues
Author-email: Alex Shtoff <alex.shtf@gmail.com>
License: Apache 2.0
License-File: LICENSE
Keywords: bspline,curves,deep-learning,differentiable,geometric-deep-learning,pytorch
Classifier: Development Status :: 3 - Alpha
Classifier: Intended Audience :: Developers
Classifier: Intended Audience :: Science/Research
Classifier: License :: OSI Approved :: MIT License
Classifier: Programming Language :: Python :: 3
Classifier: Programming Language :: Python :: 3.9
Classifier: Programming Language :: Python :: 3.10
Classifier: Programming Language :: Python :: 3.11
Classifier: Programming Language :: Python :: 3.12
Classifier: Topic :: Scientific/Engineering :: Artificial Intelligence
Classifier: Topic :: Scientific/Engineering :: Mathematics
Requires-Python: >=3.9
Requires-Dist: torch>=2.2.0
